<?xml version="1.0" encoding="utf-8" ?>
<LanguageData>
  
  <DesignatorCancel>Avbryt</DesignatorCancel>
  <DesignatorCancelDesc>Avbryt utpekt bygging, graving, frakting, innhøsting eller andre oppgaver.</DesignatorCancelDesc>

  <DesignatorCutPlants>Kutt planter</DesignatorCutPlants>
  <DesignatorCutPlantsDesc>Marker planter til nedkutting. Planten vil bli helt fjernet, all mat som befinner seg i planten blir høstet inn.</DesignatorCutPlantsDesc>

  <DesignatorDeconstruct>Dekonstruer</DesignatorDeconstruct>
  <DesignatorDeconstructDesc>Dekonstruer bygninger og gjenvinn deler av ressursene.</DesignatorDeconstructDesc>

  <DesignatorHarvest>Høst inn</DesignatorHarvest>
  <DesignatorHarvestDesc>Marker planter til å bli høstet inn som mat og andre produkter.</DesignatorHarvestDesc>

  <DesignatorHarvestWood>Kutt tre</DesignatorHarvestWood>
  <DesignatorHarvestWoodDesc>Marker trær til å bli kuttet ned til trevirke.</DesignatorHarvestWoodDesc>

  <DesignatorHaulThings>Rydd</DesignatorHaulThings>
  <DesignatorHaulThingsDesc>Marker steiner og andre ting til å bli ryddet til et sted det kan dumpes, trengs ikke for ting som mat og lik som alltid kan ryddes.</DesignatorHaulThingsDesc>
  <NothingToHaulHere>Ingenting å rydde her.</NothingToHaulHere>
  <MustHaulHaulables>Kan bare markere steiner og slagg som ikke ryddes bort automatiskt.</MustHaulHaulables>

  <DesignatorHunt>Jakt</DesignatorHunt>
  <DesignatorHuntDesc>Marker dyr til å bli jaktet av jakterne dine.</DesignatorHuntDesc>

  <DesignatorMine>Grav</DesignatorMine>
  <DesignatorMineDesc>Marker område av stein til å bli gravd ut.</DesignatorMineDesc>

  <DesignatorPlan>Planlegg</DesignatorPlan>
  <DesignatorPlanDesc>Plasser planlegging. Disse gjør ikke annet enn å hjelpe deg med fremtidige utvidelser.</DesignatorPlanDesc>

  <DesignatorPlanRemove>Fjern planlegging</DesignatorPlanRemove>
  <DesignatorPlanRemoveDesc>Fjern linjer til planlegging.</DesignatorPlanRemoveDesc>

  <DesignatorHomeRegionAdd>Utvid hjemregion</DesignatorHomeRegionAdd>
  <DesignatorHomeRegionAddDesc>Kolonister vil reparere bygninger, vaske gulv og slukke brann bare innenfor hjemregionen.</DesignatorHomeRegionAddDesc>

  <DesignatorHomeRegionRemove>Fjern fra hjemregion</DesignatorHomeRegionRemove>
  <DesignatorHomeRegionRemoveDesc>Fjerner område fra hjemregionen, kolonister vil ikke vaske, reparere eller slukke brann her.</DesignatorHomeRegionRemoveDesc>

  <DesignatorRegionNoRoofAdd>Takfritt område</DesignatorRegionNoRoofAdd>
  <DesignatorRegionNoRoofAddDesc>Lager et område hvor det ikke vil komme noen tak. Kolonister vil også rive ned eksisterende tak her.</DesignatorRegionNoRoofAddDesc>

  <DesignatorRegionNoRoofRemove>Fjern takfritt område</DesignatorRegionNoRoofRemove>
  <DesignatorRegionNoRoofRemoveDesc>Fjerner takfritt område. Tak vil dukke opp her, og eksisterende tak vil ikke bli revet ned.</DesignatorRegionNoRoofRemoveDesc>

  <DesignatorGrowingZoneDesc>Lager et område hvor kolonistene vil prøve å gro en bestemt type plante.</DesignatorGrowingZoneDesc>

  <DesignatorZoneCreateStorageResourcesDesc>Lag et nytt lager hvor kolonistene dine vil lagre ressurser.\nDette verktøyet kan også utvide ekisterende lager.</DesignatorZoneCreateStorageResourcesDesc>

  <DesignatorZoneCreateStorageDumpingDesc>Lag et nytt lager hvor kolonistene dine vil lagre søppel.\nDette verktøyet kan også utvide eksisterende søppeldynger.</DesignatorZoneCreateStorageDumpingDesc>


  <DesignatorZoneDelete>Fjern områder</DesignatorZoneDelete>
  <DesignatorZoneDeleteDesc>Fjern områder som lager og jordbruks områder.</DesignatorZoneDeleteDesc>
  
  <DesignatorClaim>Krev</DesignatorClaim>
  <DesignatorClaimDesc>Krev nøytrale strukturer til kolonien, inkluderende eldgamle ruiner og forlatte beleiringer. Strukturer eid av kolonien kan bli reparert og vedlikeholdt av dine kolonister.</DesignatorClaimDesc>
  
  
  <!-- placement of blueprints -->
  <UnchosenStuff>Mangler materiale</UnchosenStuff>
  <TooCloseToMapEdge>For nær enden av banen.</TooCloseToMapEdge>
  <OutOfBounds>Ufremkommelig</OutOfBounds>
  <CannotPlaceInUndiscovered>Kan ikke plassere i uutforsked område.</CannotPlaceInUndiscovered>
  <InteractionSpotBlocked>Bruksområde er blokkert av {0}.</InteractionSpotBlocked>
  <InteractionSpotOutOfBounds>Bruksområde er ufremkommelig.</InteractionSpotOutOfBounds>
  <InteractionSpotWillBeBlocked>Bruksområde vil bli blokkert av {0}.</InteractionSpotWillBeBlocked>
  <WouldBlockInteractionSpot>{0} ville blokkert {1}'s bruksområde.</WouldBlockInteractionSpot>
  <TerrainIsAlready>Terrenget her er allerede {0}.</TerrainIsAlready>
  <IdenticalThingExists>Identisk objekt eksisterer allerede her.</IdenticalThingExists>
  <IdenticalBlueprintExists>Identisk blåkopi eksisterer allerede her.</IdenticalBlueprintExists>
  <TerrainCannotSupport>Terrenget her kan ikke støtte dette.</TerrainCannotSupport>
  <SpaceAlreadyOccupied>Plass allerede i bruk.</SpaceAlreadyOccupied>

  
  
  <!-- placement of zones -->
  <ExpandOrCreateZone>Utvid {0} eller\nLag ny {1}</ExpandOrCreateZone>
  <CreateNewZone>Lag ny {0}</CreateNewZone>
  
  
  <!-- desc helpers -->
  <TransmitsPower>Leder strøm</TransmitsPower>


</LanguageData>