<?xml version="1.0" encoding="UTF-8"?>
<LanguageData>
  
  <!-- EN: A group of {0} from {1} have dropped in right on top of you! -->
  <CenterDrop.textEnemy>A group of {0} from {1} have dropped in right on top of you!</CenterDrop.textEnemy>
  <!-- EN: A group of friendly {0} from {1} have dropped in right on top of you! -->
  <CenterDrop.textFriendly>A group of friendly {0} from {1} have dropped in right on top of you!</CenterDrop.textFriendly>
  
  <!-- EN: A group of {0} from {1} have arrived in transport pods nearby. -->
  <EdgeDrop.textEnemy>A group of {0} from {1} have arrived in transport pods nearby.</EdgeDrop.textEnemy>
  <!-- EN: A group of friendly {0} from {1} have arrived in transport pods nearby. -->
  <EdgeDrop.textFriendly>A group of friendly {0} from {1} have arrived in transport pods nearby.</EdgeDrop.textFriendly>
  
  <!-- EN: Several separate groups of {0} from {1} have arrived in transport pods nearby. -->
  <EdgeDropGroups.textEnemy>Several separate groups of {0} from {1} have arrived in transport pods nearby.</EdgeDropGroups.textEnemy>
  <!-- EN: Several separate groups of friendly {0} from {1} have arrived in transport pods nearby. -->
  <EdgeDropGroups.textFriendly>Several separate groups of friendly {0} from {1} have arrived in transport pods nearby.</EdgeDropGroups.textFriendly>
  
  <!-- EN: A group of {0} from {1} have arrived nearby. -->
  <EdgeWalkIn.textEnemy>A group of {0} from {1} have arrived nearby.</EdgeWalkIn.textEnemy>
  <!-- EN: A group of friendly {0} from {1} have arrived nearby. -->
  <EdgeWalkIn.textFriendly>A group of friendly {0} from {1} have arrived nearby.</EdgeWalkIn.textFriendly>
  
  <!-- EN: Several separate groups of {0} from {1} have arrived nearby. -->
  <EdgeWalkInGroups.textEnemy>Several separate groups of {0} from {1} have arrived nearby.</EdgeWalkInGroups.textEnemy>
  <!-- EN: Several separate groups of friendly {0} from {1} have arrived nearby. -->
  <EdgeWalkInGroups.textFriendly>Several separate groups of friendly {0} from {1} have arrived nearby.</EdgeWalkInGroups.textFriendly>
  
  <!-- EN: A group of {0} from {1} have arrived in transport pods. Their pods went haywire and are landing scattered all over the area! -->
  <RandomDrop.textEnemy>A group of {0} from {1} have arrived in transport pods. Their pods went haywire and are landing scattered all over the area!</RandomDrop.textEnemy>
  <!-- EN: A group of friendly {0} from {1} have arrived in transport pods. Their pods went haywire and are landing scattered all over the area! -->
  <RandomDrop.textFriendly>A group of friendly {0} from {1} have arrived in transport pods. Their pods went haywire and are landing scattered all over the area!</RandomDrop.textFriendly>
  
</LanguageData>