<?xml version="1.0" encoding="utf-8" ?>
<Defs>


  <IncidentDef>
    <defName>RaidEnemy</defName>
    <workerClass>IncidentWorker_RaidEnemy</workerClass>
    <chance>9.0</chance>
    <favorability>Bad</favorability>
    <category>ThreatBig</category>
    <pointsScaleable>true</pointsScaleable>
  </IncidentDef>

  <IncidentDef>
    <defName>AnimalInsanity</defName>
    <workerClass>IncidentWorker_AnimalInsanity</workerClass>
    <chance>1.0</chance>
    <minRefireDays>1</minRefireDays>
    <favorability>VeryBad</favorability>
    <category>ThreatBig</category>
    <pointsScaleable>true</pointsScaleable>
  </IncidentDef>

  <IncidentDef>
    <defName>ShipPartCrash</defName>
    <workerClass>IncidentWorker_ShipPartCrash</workerClass>
    <chance>1.5</chance>
    <minRefireDays>30</minRefireDays>
    <favorability>Bad</favorability>
    <category>ThreatBig</category>
    <pointsScaleable>true</pointsScaleable>
    <minThreatPoints>250</minThreatPoints>
  </IncidentDef>


</Defs>